{"ToAddresses":"melodia.nocturnis@gmail.com", "CcAddresses":"testdetruc@maderation.net", "Body1":"Bonjour,<br><br>veuillez trouver ci-joint le document pour votre devis madera : <a href='https://maderationpictures.s3-eu-west-1.amazonaws.com/projetno1-ZGltLiBqYW52LiAxMiAyMDIwIDIzOjAzOjUy.pdf'>Au format PDF</a><a href='https://maderationpictures.s3-eu-west-1.amazonaws.com/projetno1-ZGltLiBqYW52LiAxMiAyMDIwIDIzOjAzOjUy.html'>Au format HTML</a><br><br>Cordialement,<br>L'équipe Madera", "Body2":"", "Subject":"Votre devis de projet no 1"}